<?xml version="1.0" encoding="UTF-8"?>
<tv >
<channel id="法治天地">
<display-name lang="zh">法治天地</display-name>
</channel>
<channel id="动漫秀场">
<display-name lang="zh">动漫秀场</display-name>
</channel>
<channel id="亚洲电影">
<display-name lang="zh">亚洲电影</display-name>
</channel>
<channel id="欧美电影">
<display-name lang="zh">欧美电影</display-name>
</channel>
<channel id="IPTV相声小品">
<display-name lang="zh">IPTV相声小品</display-name>
</channel>
<channel id="IPTV法治">
<display-name lang="zh">IPTV法治</display-name>
</channel>
<channel id="IPTV3+">
<display-name lang="zh">IPTV3+</display-name>
</channel>
<channel id="IPTV5+">
<display-name lang="zh">IPTV5+</display-name>
</channel>
<channel id="IPTV6+">
<display-name lang="zh">IPTV6+</display-name>
</channel>
<channel id="IPTV8+">
<display-name lang="zh">IPTV8+</display-name>
</channel>
<channel id="济南综合">
<display-name lang="zh">济南综合</display-name>
</channel>
<channel id="临沂综合">
<display-name lang="zh">临沂综合</display-name>
</channel>
<channel id="临沂农科">
<display-name lang="zh">临沂农科</display-name>
</channel>
<channel id="临沂公共">
<display-name lang="zh">临沂公共</display-name>
</channel>
<programme start="20210202000000 +0800" stop="20210202060000 +0800" channel="法治天地">
<title lang="zh">和大律师面对面</title>
</programme>
<programme start="20210202060000 +0800" stop="20210202062000 +0800" channel="法治天地">
<title lang="zh">律师界2(8)</title>
</programme>
<programme start="20210202062000 +0800" stop="20210202063000 +0800" channel="法治天地">
<title lang="zh">首届上海检察风云演说会:周子简</title>
</programme>
<programme start="20210202063000 +0800" stop="20210202070000 +0800" channel="法治天地">
<title lang="zh">和大律师面对面</title>
</programme>
<programme start="20210202070000 +0800" stop="20210202071000 +0800" channel="法治天地">
<title lang="zh">禁毒视窗</title>
</programme>
<programme start="20210202071000 +0800" stop="20210202072000 +0800" channel="法治天地">
<title lang="zh">首届上海检察风云演说会</title>
</programme>
<programme start="20210202072000 +0800" stop="20210202073000 +0800" channel="法治天地">
<title lang="zh">法说百姓事(18)</title>
</programme>
<programme start="20210202073000 +0800" stop="20210202075000 +0800" channel="法治天地">
<title lang="zh">记者调查</title>
</programme>
<programme start="20210202075000 +0800" stop="20210202080000 +0800" channel="法治天地">
<title lang="zh">法眼看生活</title>
</programme>
<programme start="20210202080000 +0800" stop="20210202082000 +0800" channel="法治天地">
<title lang="zh">律师界2(8)</title>
</programme>
<programme start="20210202082000 +0800" stop="20210202083000 +0800" channel="法治天地">
<title lang="zh">首届上海检察风云演说会</title>
</programme>
<programme start="20210202083000 +0800" stop="20210202090000 +0800" channel="法治天地">
<title lang="zh">和大律师面对面</title>
</programme>
<programme start="20210202090000 +0800" stop="20210202090400 +0800" channel="法治天地">
<title lang="zh">中国梦:此生最爱是梨园</title>
</programme>
<programme start="20210202090400 +0800" stop="20210202094600 +0800" channel="法治天地">
<title lang="zh">大丈夫的私房钱</title>
</programme>
<programme start="20210202094600 +0800" stop="20210202103000 +0800" channel="法治天地">
<title lang="zh">吵不完的小夫妻</title>
</programme>
<programme start="20210202103000 +0800" stop="20210202110000 +0800" channel="法治天地">
<title lang="zh">和大律师面对面</title>
</programme>
<programme start="20210202110000 +0800" stop="20210202111000 +0800" channel="法治天地">
<title lang="zh">禁毒视窗</title>
</programme>
<programme start="20210202111000 +0800" stop="20210202112000 +0800" channel="法治天地">
<title lang="zh">法说百姓事:郑健</title>
</programme>
<programme start="20210202112000 +0800" stop="20210202113000 +0800" channel="法治天地">
<title lang="zh">法眼看生活</title>
</programme>
<programme start="20210202113000 +0800" stop="20210203000000 +0800" channel="法治天地">
<title lang="zh">法治新闻</title>
</programme>
<programme start="20210203000000 +0800" stop="20210203003000 +0800" channel="法治天地">
<title lang="zh">和大律师面对面</title>
</programme>
<programme start="20210203003000 +0800" stop="20210203004000 +0800" channel="法治天地">
<title lang="zh">首届上海检察风云演说会</title>
</programme>
<programme start="20210203004000 +0800" stop="20210203012300 +0800" channel="法治天地">
<title lang="zh">疯狂的爱(上)</title>
</programme>
<programme start="20210203012300 +0800" stop="20210203020500 +0800" channel="法治天地">
<title lang="zh">疯狂的爱(下)</title>
</programme>
<programme start="20210203020500 +0800" stop="20210203022600 +0800" channel="法治天地">
<title lang="zh">律师讲堂(921):马骏</title>
</programme>
<programme start="20210203022600 +0800" stop="20210203023000 +0800" channel="法治天地">
<title lang="zh">MV:这里有我</title>
</programme>
<programme start="20210203023000 +0800" stop="20210203030000 +0800" channel="法治天地">
<title lang="zh">和大律师面对面</title>
</programme>
<programme start="20210203030000 +0800" stop="20210203032000 +0800" channel="法治天地">
<title lang="zh">律师界2(7):企业降薪之争</title>
</programme>
<programme start="20210203032000 +0800" stop="20210203033000 +0800" channel="法治天地">
<title lang="zh">首届上海检察风云演说会</title>
</programme>
<programme start="20210203033000 +0800" stop="20210203035000 +0800" channel="法治天地">
<title lang="zh">记者调查</title>
</programme>
<programme start="20210203035000 +0800" stop="20210203035800 +0800" channel="法治天地">
<title lang="zh">首届上海检察风云演说会:高峰</title>
</programme>
<programme start="20210203035800 +0800" stop="20210203040600 +0800" channel="法治天地">
<title lang="zh">首届上海检察风云演说会:谷晓丽</title>
</programme>
<programme start="20210203040600 +0800" stop="20210203044900 +0800" channel="法治天地">
<title lang="zh">疯狂的爱(上)</title>
</programme>
<programme start="20210203044900 +0800" stop="20210203053000 +0800" channel="法治天地">
<title lang="zh">疯狂的爱(下)</title>
</programme>
<programme start="20210203053000 +0800" stop="20210203060000 +0800" channel="法治天地">
<title lang="zh">和大律师面对面</title>
</programme>
<programme start="20210203060000 +0800" stop="20210203062500 +0800" channel="法治天地">
<title lang="zh">庭审直播精编版(918)</title>
</programme>
<programme start="20210203062500 +0800" stop="20210203063000 +0800" channel="法治天地">
<title lang="zh">MV:这里有我</title>
</programme>
<programme start="20210203063000 +0800" stop="20210203070000 +0800" channel="法治天地">
<title lang="zh">和大律师面对面</title>
</programme>
<programme start="20210203070000 +0800" stop="20210203072000 +0800" channel="法治天地">
<title lang="zh">律师讲堂(921):马骏</title>
</programme>
<programme start="20210203072000 +0800" stop="20210203073000 +0800" channel="法治天地">
<title lang="zh">法说百姓事:郑健</title>
</programme>
<programme start="20210203073000 +0800" stop="20210203075000 +0800" channel="法治天地">
<title lang="zh">记者调查</title>
</programme>
<programme start="20210203075000 +0800" stop="20210203080000 +0800" channel="法治天地">
<title lang="zh">法眼看生活</title>
</programme>
<programme start="20210203080000 +0800" stop="20210203082500 +0800" channel="法治天地">
<title lang="zh">庭审直播精编版(918)</title>
</programme>
<programme start="20210203082500 +0800" stop="20210203083000 +0800" channel="法治天地">
<title lang="zh">MV:这里有我</title>
</programme>
<programme start="20210203083000 +0800" stop="20210203090000 +0800" channel="法治天地">
<title lang="zh">和大律师面对面</title>
</programme>
<programme start="20210203090000 +0800" stop="20210203090600 +0800" channel="法治天地">
<title lang="zh">老交警与新司机3(2)</title>
</programme>
<programme start="20210203090600 +0800" stop="20210203094900 +0800" channel="法治天地">
<title lang="zh">疯狂的爱(上)</title>
</programme>
<programme start="20210203094900 +0800" stop="20210203103000 +0800" channel="法治天地">
<title lang="zh">疯狂的爱(下)</title>
</programme>
<programme start="20210203103000 +0800" stop="20210203110000 +0800" channel="法治天地">
<title lang="zh">和大律师面对面</title>
</programme>
<programme start="20210203110000 +0800" stop="20210203112000 +0800" channel="法治天地">
<title lang="zh">律师讲堂(921):马骏</title>
</programme>
<programme start="20210203112000 +0800" stop="20210203113000 +0800" channel="法治天地">
<title lang="zh">法眼看生活</title>
</programme>
<programme start="20210203113000 +0800" stop="20210203235950 +0800" channel="法治天地">
<title lang="zh">法治新闻</title>
</programme>
<programme start="20210202000000 +0800" stop="20210202001300 +0800" channel="动漫秀场">
<title lang="zh">宇宙护卫队2(16)</title>
</programme>
<programme start="20210202001300 +0800" stop="20210202002500 +0800" channel="动漫秀场">
<title lang="zh">宇宙护卫队2(17)</title>
</programme>
<programme start="20210202002500 +0800" stop="20210202060000 +0800" channel="动漫秀场">
<title lang="zh">少儿动画精彩</title>
</programme>
<programme start="20210202060000 +0800" stop="20210202061400 +0800" channel="动漫秀场">
<title lang="zh">猪猪侠之竞速小英雄2(8)</title>
</programme>
<programme start="20210202061400 +0800" stop="20210202063000 +0800" channel="动漫秀场">
<title lang="zh">猪猪侠之竞速小英雄2(9)</title>
</programme>
<programme start="20210202063000 +0800" stop="20210202064600 +0800" channel="动漫秀场">
<title lang="zh">猪猪侠之竞速小英雄2(10)</title>
</programme>
<programme start="20210202064600 +0800" stop="20210202070100 +0800" channel="动漫秀场">
<title lang="zh">猪猪侠之竞速小英雄2(11)</title>
</programme>
<programme start="20210202070100 +0800" stop="20210202071300 +0800" channel="动漫秀场">
<title lang="zh">甜心格格-不可能的任务(15)</title>
</programme>
<programme start="20210202071300 +0800" stop="20210202072700 +0800" channel="动漫秀场">
<title lang="zh">甜心格格-不可能的任务(16)</title>
</programme>
<programme start="20210202072700 +0800" stop="20210202074000 +0800" channel="动漫秀场">
<title lang="zh">甜心格格-不可能的任务(17)</title>
</programme>
<programme start="20210202074000 +0800" stop="20210202075300 +0800" channel="动漫秀场">
<title lang="zh">甜心格格-不可能的任务(18)</title>
</programme>
<programme start="20210202075300 +0800" stop="20210202080000 +0800" channel="动漫秀场">
<title lang="zh">少儿动画精彩</title>
</programme>
<programme start="20210202080000 +0800" stop="20210202081200 +0800" channel="动漫秀场">
<title lang="zh">宇宙护卫队2(20)</title>
</programme>
<programme start="20210202081200 +0800" stop="20210202082400 +0800" channel="动漫秀场">
<title lang="zh">宇宙护卫队2(21)</title>
</programme>
<programme start="20210202082400 +0800" stop="20210202083700 +0800" channel="动漫秀场">
<title lang="zh">开心超人联盟之英雄归来(6)</title>
</programme>
<programme start="20210202083700 +0800" stop="20210202085200 +0800" channel="动漫秀场">
<title lang="zh">开心超人联盟之英雄归来(7)</title>
</programme>
<programme start="20210202085200 +0800" stop="20210202090400 +0800" channel="动漫秀场">
<title lang="zh">超级飞侠7(14)</title>
</programme>
<programme start="20210202090400 +0800" stop="20210202091700 +0800" channel="动漫秀场">
<title lang="zh">超级飞侠7(15)</title>
</programme>
<programme start="20210202091700 +0800" stop="20210202092900 +0800" channel="动漫秀场">
<title lang="zh">帮帮龙出动2(11)</title>
</programme>
<programme start="20210202092900 +0800" stop="20210202094200 +0800" channel="动漫秀场">
<title lang="zh">帮帮龙出动2(12)</title>
</programme>
<programme start="20210202094200 +0800" stop="20210202095500 +0800" channel="动漫秀场">
<title lang="zh">帮帮龙出动2(13)</title>
</programme>
<programme start="20210202095500 +0800" stop="20210202101000 +0800" channel="动漫秀场">
<title lang="zh">猪猪侠之竞速小英雄2(12)</title>
</programme>
<programme start="20210202101000 +0800" stop="20210202102500 +0800" channel="动漫秀场">
<title lang="zh">猪猪侠之竞速小英雄2(13)</title>
</programme>
<programme start="20210202102500 +0800" stop="20210202104100 +0800" channel="动漫秀场">
<title lang="zh">猪猪侠之竞速小英雄2(14)</title>
</programme>
<programme start="20210202104100 +0800" stop="20210202105800 +0800" channel="动漫秀场">
<title lang="zh">猪猪侠之竞速小英雄2(15)</title>
</programme>
<programme start="20210202105800 +0800" stop="20210202111100 +0800" channel="动漫秀场">
<title lang="zh">甜心格格-不可能的任务(19)</title>
</programme>
<programme start="20210202111100 +0800" stop="20210202112500 +0800" channel="动漫秀场">
<title lang="zh">甜心格格-不可能的任务(20)</title>
</programme>
<programme start="20210202112500 +0800" stop="20210202113900 +0800" channel="动漫秀场">
<title lang="zh">甜心格格-不可能的任务(21)</title>
</programme>
<programme start="20210202113900 +0800" stop="20210202115200 +0800" channel="动漫秀场">
<title lang="zh">甜心格格-不可能的任务(22)</title>
</programme>
<programme start="20210202115200 +0800" stop="20210203000000 +0800" channel="动漫秀场">
<title lang="zh">少儿动画精彩</title>
</programme>
<programme start="20210203000000 +0800" stop="20210203001200 +0800" channel="动漫秀场">
<title lang="zh">宇宙护卫队2(18)</title>
</programme>
<programme start="20210203001200 +0800" stop="20210203002500 +0800" channel="动漫秀场">
<title lang="zh">宇宙护卫队2(19)</title>
</programme>
<programme start="20210203002500 +0800" stop="20210203003700 +0800" channel="动漫秀场">
<title lang="zh">开心超人联盟之英雄归来(4)</title>
</programme>
<programme start="20210203003700 +0800" stop="20210203005000 +0800" channel="动漫秀场">
<title lang="zh">开心超人联盟之英雄归来(5)</title>
</programme>
<programme start="20210203005000 +0800" stop="20210203010300 +0800" channel="动漫秀场">
<title lang="zh">超级飞侠7(12)</title>
</programme>
<programme start="20210203010300 +0800" stop="20210203011600 +0800" channel="动漫秀场">
<title lang="zh">超级飞侠7(13)</title>
</programme>
<programme start="20210203011600 +0800" stop="20210203012900 +0800" channel="动漫秀场">
<title lang="zh">帮帮龙出动2(8)</title>
</programme>
<programme start="20210203012900 +0800" stop="20210203014100 +0800" channel="动漫秀场">
<title lang="zh">帮帮龙出动2(9)</title>
</programme>
<programme start="20210203014100 +0800" stop="20210203015400 +0800" channel="动漫秀场">
<title lang="zh">帮帮龙出动2(10)</title>
</programme>
<programme start="20210203015400 +0800" stop="20210203020900 +0800" channel="动漫秀场">
<title lang="zh">猪猪侠之竞速小英雄2(8)</title>
</programme>
<programme start="20210203020900 +0800" stop="20210203022500 +0800" channel="动漫秀场">
<title lang="zh">猪猪侠之竞速小英雄2(9)</title>
</programme>
<programme start="20210203022500 +0800" stop="20210203024000 +0800" channel="动漫秀场">
<title lang="zh">猪猪侠之竞速小英雄2(10)</title>
</programme>
<programme start="20210203024000 +0800" stop="20210203025500 +0800" channel="动漫秀场">
<title lang="zh">猪猪侠之竞速小英雄2(11)</title>
</programme>
<programme start="20210203025500 +0800" stop="20210203030800 +0800" channel="动漫秀场">
<title lang="zh">甜心格格-不可能的任务(15)</title>
</programme>
<programme start="20210203030800 +0800" stop="20210203032100 +0800" channel="动漫秀场">
<title lang="zh">甜心格格-不可能的任务(16)</title>
</programme>
<programme start="20210203032100 +0800" stop="20210203033400 +0800" channel="动漫秀场">
<title lang="zh">甜心格格-不可能的任务(17)</title>
</programme>
<programme start="20210203033400 +0800" stop="20210203034700 +0800" channel="动漫秀场">
<title lang="zh">甜心格格-不可能的任务(18)</title>
</programme>
<programme start="20210203034700 +0800" stop="20210203040000 +0800" channel="动漫秀场">
<title lang="zh">少儿动画精彩</title>
</programme>
<programme start="20210203040000 +0800" stop="20210203041200 +0800" channel="动漫秀场">
<title lang="zh">宇宙护卫队2(20)</title>
</programme>
<programme start="20210203041200 +0800" stop="20210203042500 +0800" channel="动漫秀场">
<title lang="zh">宇宙护卫队2(21)</title>
</programme>
<programme start="20210203042500 +0800" stop="20210203043800 +0800" channel="动漫秀场">
<title lang="zh">开心超人联盟之英雄归来(6)</title>
</programme>
<programme start="20210203043800 +0800" stop="20210203045100 +0800" channel="动漫秀场">
<title lang="zh">开心超人联盟之英雄归来(7)</title>
</programme>
<programme start="20210203045100 +0800" stop="20210203050300 +0800" channel="动漫秀场">
<title lang="zh">超级飞侠7(14)</title>
</programme>
<programme start="20210203050300 +0800" stop="20210203051600 +0800" channel="动漫秀场">
<title lang="zh">超级飞侠7(15)</title>
</programme>
<programme start="20210203051600 +0800" stop="20210203052800 +0800" channel="动漫秀场">
<title lang="zh">帮帮龙出动2(11)</title>
</programme>
<programme start="20210203052800 +0800" stop="20210203054100 +0800" channel="动漫秀场">
<title lang="zh">帮帮龙出动2(12)</title>
</programme>
<programme start="20210203054100 +0800" stop="20210203055300 +0800" channel="动漫秀场">
<title lang="zh">帮帮龙出动2(13)</title>
</programme>
<programme start="20210203055300 +0800" stop="20210203060800 +0800" channel="动漫秀场">
<title lang="zh">猪猪侠之竞速小英雄2(12)</title>
</programme>
<programme start="20210203060800 +0800" stop="20210203062300 +0800" channel="动漫秀场">
<title lang="zh">猪猪侠之竞速小英雄2(13)</title>
</programme>
<programme start="20210203062300 +0800" stop="20210203063800 +0800" channel="动漫秀场">
<title lang="zh">猪猪侠之竞速小英雄2(14)</title>
</programme>
<programme start="20210203063800 +0800" stop="20210203065400 +0800" channel="动漫秀场">
<title lang="zh">猪猪侠之竞速小英雄2(15)</title>
</programme>
<programme start="20210203065400 +0800" stop="20210203070000 +0800" channel="动漫秀场">
<title lang="zh">少儿动画精彩</title>
</programme>
<programme start="20210203070000 +0800" stop="20210203071400 +0800" channel="动漫秀场">
<title lang="zh">甜心格格-不可能的任务(19)</title>
</programme>
<programme start="20210203071400 +0800" stop="20210203072700 +0800" channel="动漫秀场">
<title lang="zh">甜心格格-不可能的任务(20)</title>
</programme>
<programme start="20210203072700 +0800" stop="20210203074100 +0800" channel="动漫秀场">
<title lang="zh">甜心格格-不可能的任务(21)</title>
</programme>
<programme start="20210203074100 +0800" stop="20210203080000 +0800" channel="动漫秀场">
<title lang="zh">甜心格格-不可能的任务(22)</title>
</programme>
<programme start="20210203080000 +0800" stop="20210203081200 +0800" channel="动漫秀场">
<title lang="zh">宇宙护卫队2(22)</title>
</programme>
<programme start="20210203081200 +0800" stop="20210203082500 +0800" channel="动漫秀场">
<title lang="zh">宇宙护卫队2(23)</title>
</programme>
<programme start="20210203082500 +0800" stop="20210203083800 +0800" channel="动漫秀场">
<title lang="zh">开心超人联盟之英雄归来(8)</title>
</programme>
<programme start="20210203083800 +0800" stop="20210203085200 +0800" channel="动漫秀场">
<title lang="zh">开心超人联盟之英雄归来(9)</title>
</programme>
<programme start="20210203085200 +0800" stop="20210203090500 +0800" channel="动漫秀场">
<title lang="zh">超级飞侠7(16)</title>
</programme>
<programme start="20210203090500 +0800" stop="20210203091800 +0800" channel="动漫秀场">
<title lang="zh">超级飞侠7(17)</title>
</programme>
<programme start="20210203091800 +0800" stop="20210203093000 +0800" channel="动漫秀场">
<title lang="zh">帮帮龙出动2(14)</title>
</programme>
<programme start="20210203093000 +0800" stop="20210203094200 +0800" channel="动漫秀场">
<title lang="zh">帮帮龙出动2(15)</title>
</programme>
<programme start="20210203094200 +0800" stop="20210203095600 +0800" channel="动漫秀场">
<title lang="zh">帮帮龙出动2(16)</title>
</programme>
<programme start="20210203095600 +0800" stop="20210203101100 +0800" channel="动漫秀场">
<title lang="zh">猪猪侠之竞速小英雄2(16)</title>
</programme>
<programme start="20210203101100 +0800" stop="20210203102600 +0800" channel="动漫秀场">
<title lang="zh">猪猪侠之竞速小英雄2(17)</title>
</programme>
<programme start="20210203102600 +0800" stop="20210203104100 +0800" channel="动漫秀场">
<title lang="zh">猪猪侠之竞速小英雄2(18)</title>
</programme>
<programme start="20210203104100 +0800" stop="20210203110000 +0800" channel="动漫秀场">
<title lang="zh">猪猪侠之竞速小英雄2(19)</title>
</programme>
<programme start="20210203110000 +0800" stop="20210203111300 +0800" channel="动漫秀场">
<title lang="zh">甜心格格-不可能的任务(23)</title>
</programme>
<programme start="20210203111300 +0800" stop="20210203112700 +0800" channel="动漫秀场">
<title lang="zh">甜心格格-不可能的任务(24)</title>
</programme>
<programme start="20210203112700 +0800" stop="20210203114000 +0800" channel="动漫秀场">
<title lang="zh">甜心格格-不可能的任务(25)</title>
</programme>
<programme start="20210203114000 +0800" stop="20210203115500 +0800" channel="动漫秀场">
<title lang="zh">甜心格格5(26)</title>
</programme>
<programme start="20210203115500 +0800" stop="20210203235950 +0800" channel="动漫秀场">
<title lang="zh">少儿动画精彩</title>
</programme>
<programme start="20210202013800 +0800" stop="20210202030700 +0800" channel="亚洲电影">
<title lang="zh">歌舞青春</title>
</programme>
<programme start="20210202030700 +0800" stop="20210202043600 +0800" channel="亚洲电影">
<title lang="zh">甜水谣</title>
</programme>
<programme start="20210202043600 +0800" stop="20210202050000 +0800" channel="亚洲电影">
<title lang="zh">实境之旅:桂林</title>
</programme>
<programme start="20210202050000 +0800" stop="20210202070400 +0800" channel="亚洲电影">
<title lang="zh">正义罪犯</title>
</programme>
<programme start="20210202070400 +0800" stop="20210202084000 +0800" channel="亚洲电影">
<title lang="zh">暴疯语</title>
</programme>
<programme start="20210202084000 +0800" stop="20210202102200 +0800" channel="亚洲电影">
<title lang="zh">河东狮吼2</title>
</programme>
<programme start="20210202102200 +0800" stop="20210203003500 +0800" channel="亚洲电影">
<title lang="zh">花木兰2020版</title>
</programme>
<programme start="20210203003500 +0800" stop="20210203013900 +0800" channel="亚洲电影">
<title lang="zh">血拳之龙虎斗</title>
</programme>
<programme start="20210203013900 +0800" stop="20210203034200 +0800" channel="亚洲电影">
<title lang="zh">永远的托词</title>
</programme>
<programme start="20210203034200 +0800" stop="20210203050000 +0800" channel="亚洲电影">
<title lang="zh">实境之旅:桂林</title>
</programme>
<programme start="20210203050000 +0800" stop="20210203065100 +0800" channel="亚洲电影">
<title lang="zh">花木兰2020版</title>
</programme>
<programme start="20210203065100 +0800" stop="20210203082600 +0800" channel="亚洲电影">
<title lang="zh">在世界中心呼唤爱</title>
</programme>
<programme start="20210203082600 +0800" stop="20210203101900 +0800" channel="亚洲电影">
<title lang="zh">气息</title>
</programme>
<programme start="20210203101900 +0800" stop="20210203235950 +0800" channel="亚洲电影">
<title lang="zh">镰仓物语</title>
</programme>
<programme start="20210202002800 +0800" stop="20210202023300 +0800" channel="欧美电影">
<title lang="zh">环太平洋</title>
</programme>
<programme start="20210202023300 +0800" stop="20210202041800 +0800" channel="欧美电影">
<title lang="zh">机器战警3</title>
</programme>
<programme start="20210202041800 +0800" stop="20210202050000 +0800" channel="欧美电影">
<title lang="zh">情迷英格兰</title>
</programme>
<programme start="20210202050000 +0800" stop="20210202062000 +0800" channel="欧美电影">
<title lang="zh">绝美监狱</title>
</programme>
<programme start="20210202062000 +0800" stop="20210202083300 +0800" channel="欧美电影">
<title lang="zh">X特遣队</title>
</programme>
<programme start="20210202083300 +0800" stop="20210202100400 +0800" channel="欧美电影">
<title lang="zh">自由坠落</title>
</programme>
<programme start="20210202100400 +0800" stop="20210203003600 +0800" channel="欧美电影">
<title lang="zh">奎迪-英雄再起</title>
</programme>
<programme start="20210203003600 +0800" stop="20210203021600 +0800" channel="欧美电影">
<title lang="zh">猫女</title>
</programme>
<programme start="20210203021600 +0800" stop="20210203043700 +0800" channel="欧美电影">
<title lang="zh">美国队长3</title>
</programme>
<programme start="20210203043700 +0800" stop="20210203050000 +0800" channel="欧美电影">
<title lang="zh">情迷英格兰</title>
</programme>
<programme start="20210203050000 +0800" stop="20210203070900 +0800" channel="欧美电影">
<title lang="zh">奎迪-英雄再起</title>
</programme>
<programme start="20210203070900 +0800" stop="20210203085400 +0800" channel="欧美电影">
<title lang="zh">偷天换日</title>
</programme>
<programme start="20210203085400 +0800" stop="20210203110300 +0800" channel="欧美电影">
<title lang="zh">缩小人生</title>
</programme>
<programme start="20210203110300 +0800" stop="20210203235950 +0800" channel="欧美电影">
<title lang="zh">洛奇5</title>
</programme>
<programme start="20210202182000 +0800" stop="20210202014500 +0800" channel="IPTV相声小品">
<title lang="zh"></title>
</programme>
<programme start="20210202014500 +0800" stop="20210202030000 +0800" channel="IPTV相声小品">
<title lang="zh">《乡村大世界》 20180113 小镇外传</title>
</programme>
<programme start="20210202030000 +0800" stop="20210202041700 +0800" channel="IPTV相声小品">
<title lang="zh">《综艺盛典》 20180111 今晚看你的</title>
</programme>
<programme start="20210202041700 +0800" stop="20210202055000 +0800" channel="IPTV相声小品">
<title lang="zh">《星光大道》 20190112</title>
</programme>
<programme start="20210202055000 +0800" stop="20210202182000 +0800" channel="IPTV相声小品">
<title lang="zh">《我爱满堂彩》 20190320 四方迎春 第二站</title>
</programme>
<programme start="20210202182000 +0800" stop="20210202080700 +0800" channel="IPTV相声小品">
<title lang="zh"></title>
</programme>
<programme start="20210202080700 +0800" stop="20210202092200 +0800" channel="IPTV相声小品">
<title lang="zh">《乡村大世界》 20180113 小镇外传</title>
</programme>
<programme start="20210202092200 +0800" stop="20210202103900 +0800" channel="IPTV相声小品">
<title lang="zh">《综艺盛典》 20180111 今晚看你的</title>
</programme>
<programme start="20210202103900 +0800" stop="20210203004700 +0800" channel="IPTV相声小品">
<title lang="zh">《星光大道》 20190112</title>
</programme>
<programme start="20210203004700 +0800" stop="20210203020400 +0800" channel="IPTV相声小品">
<title lang="zh">综艺喜乐汇</title>
</programme>
<programme start="20210203020400 +0800" stop="20210203034200 +0800" channel="IPTV相声小品">
<title lang="zh">星光大道</title>
</programme>
<programme start="20210203034200 +0800" stop="20210203045400 +0800" channel="IPTV相声小品">
<title lang="zh">乡村大世界</title>
</programme>
<programme start="20210203045400 +0800" stop="20210203061100 +0800" channel="IPTV相声小品">
<title lang="zh">综艺盛典</title>
</programme>
<programme start="20210203061100 +0800" stop="20210203072700 +0800" channel="IPTV相声小品">
<title lang="zh">我要上春晚</title>
</programme>
<programme start="20210203072700 +0800" stop="20210203081400 +0800" channel="IPTV相声小品">
<title lang="zh">锦绣梨园</title>
</programme>
<programme start="20210203081400 +0800" stop="20210203093100 +0800" channel="IPTV相声小品">
<title lang="zh">我爱满堂彩</title>
</programme>
<programme start="20210203093100 +0800" stop="20210203104800 +0800" channel="IPTV相声小品">
<title lang="zh">综艺喜乐汇</title>
</programme>
<programme start="20210203104800 +0800" stop="20210203235950 +0800" channel="IPTV相声小品">
<title lang="zh">星光大道</title>
</programme>
<programme start="20210202000900 +0800" stop="20210202002600 +0800" channel="IPTV法治">
<title lang="zh">《道德观察(日播版)》 20200611 勇往直前</title>
</programme>
<programme start="20210202002600 +0800" stop="20210202005300 +0800" channel="IPTV法治">
<title lang="zh">《法律讲堂(文史版)》 20180205 《红楼梦》成书传世之谜(三)</title>
</programme>
<programme start="20210202005300 +0800" stop="20210202012000 +0800" channel="IPTV法治">
<title lang="zh">《法律讲堂(文史版)》 20180206 《红楼梦》成书传世之谜(四)</title>
</programme>
<programme start="20210202012000 +0800" stop="20210202014700 +0800" channel="IPTV法治">
<title lang="zh">《热线12》 20200602</title>
</programme>
<programme start="20210202014700 +0800" stop="20210202021400 +0800" channel="IPTV法治">
<title lang="zh">《热线12》 20200603</title>
</programme>
<programme start="20210202021400 +0800" stop="20210202023100 +0800" channel="IPTV法治">
<title lang="zh">《道德观察(日播版)》 20200610 一路逆行</title>
</programme>
<programme start="20210202023100 +0800" stop="20210202024900 +0800" channel="IPTV法治">
<title lang="zh">《道德观察(日播版)》 20200611 勇往直前</title>
</programme>
<programme start="20210202024900 +0800" stop="20210202031500 +0800" channel="IPTV法治">
<title lang="zh">《法律讲堂(文史版)》 20180205 《红楼梦》成书传世之谜(三)</title>
</programme>
<programme start="20210202031500 +0800" stop="20210202034200 +0800" channel="IPTV法治">
<title lang="zh">《法律讲堂(文史版)》 20180206 《红楼梦》成书传世之谜(四)</title>
</programme>
<programme start="20210202034200 +0800" stop="20210202040900 +0800" channel="IPTV法治">
<title lang="zh">《热线12》 20200602</title>
</programme>
<programme start="20210202040900 +0800" stop="20210202043600 +0800" channel="IPTV法治">
<title lang="zh">《热线12》 20200603</title>
</programme>
<programme start="20210202043600 +0800" stop="20210202045400 +0800" channel="IPTV法治">
<title lang="zh">《道德观察(日播版)》 20200610 一路逆行</title>
</programme>
<programme start="20210202045400 +0800" stop="20210202051200 +0800" channel="IPTV法治">
<title lang="zh">《道德观察(日播版)》 20200611 勇往直前</title>
</programme>
<programme start="20210202051200 +0800" stop="20210202053900 +0800" channel="IPTV法治">
<title lang="zh">《法律讲堂(文史版)》 20180205 《红楼梦》成书传世之谜(三)</title>
</programme>
<programme start="20210202053900 +0800" stop="20210202060600 +0800" channel="IPTV法治">
<title lang="zh">《法律讲堂(文史版)》 20180206 《红楼梦》成书传世之谜(四)</title>
</programme>
<programme start="20210202060600 +0800" stop="20210202063200 +0800" channel="IPTV法治">
<title lang="zh">《热线12》 20200602</title>
</programme>
<programme start="20210202063200 +0800" stop="20210202065900 +0800" channel="IPTV法治">
<title lang="zh">《热线12》 20200603</title>
</programme>
<programme start="20210202065900 +0800" stop="20210202071700 +0800" channel="IPTV法治">
<title lang="zh">《道德观察(日播版)》 20200610 一路逆行</title>
</programme>
<programme start="20210202071700 +0800" stop="20210202073400 +0800" channel="IPTV法治">
<title lang="zh">《道德观察(日播版)》 20200611 勇往直前</title>
</programme>
<programme start="20210202073400 +0800" stop="20210202080100 +0800" channel="IPTV法治">
<title lang="zh">《法律讲堂(文史版)》 20180205 《红楼梦》成书传世之谜(三)</title>
</programme>
<programme start="20210202080100 +0800" stop="20210202082800 +0800" channel="IPTV法治">
<title lang="zh">《法律讲堂(文史版)》 20180206 《红楼梦》成书传世之谜(四)</title>
</programme>
<programme start="20210202082800 +0800" stop="20210202085500 +0800" channel="IPTV法治">
<title lang="zh">《热线12》 20200602</title>
</programme>
<programme start="20210202085500 +0800" stop="20210202092200 +0800" channel="IPTV法治">
<title lang="zh">《热线12》 20200603</title>
</programme>
<programme start="20210202092200 +0800" stop="20210202093900 +0800" channel="IPTV法治">
<title lang="zh">《道德观察(日播版)》 20200610 一路逆行</title>
</programme>
<programme start="20210202093900 +0800" stop="20210202095700 +0800" channel="IPTV法治">
<title lang="zh">《道德观察(日播版)》 20200611 勇往直前</title>
</programme>
<programme start="20210202095700 +0800" stop="20210202102400 +0800" channel="IPTV法治">
<title lang="zh">《法律讲堂(文史版)》 20180205 《红楼梦》成书传世之谜(三)</title>
</programme>
<programme start="20210202102400 +0800" stop="20210202105100 +0800" channel="IPTV法治">
<title lang="zh">《法律讲堂(文史版)》 20180206 《红楼梦》成书传世之谜(四)</title>
</programme>
<programme start="20210202105100 +0800" stop="20210202111800 +0800" channel="IPTV法治">
<title lang="zh">《热线12》 20200602</title>
</programme>
<programme start="20210202111800 +0800" stop="20210202114500 +0800" channel="IPTV法治">
<title lang="zh">《热线12》 20200603</title>
</programme>
<programme start="20210202114500 +0800" stop="20210203001500 +0800" channel="IPTV法治">
<title lang="zh">《道德观察(日播版)》 20200610 一路逆行</title>
</programme>
<programme start="20210203001500 +0800" stop="20210203010800 +0800" channel="IPTV法治">
<title lang="zh">法律讲堂(生活版)</title>
</programme>
<programme start="20210203010800 +0800" stop="20210203013900 +0800" channel="IPTV法治">
<title lang="zh">一线</title>
</programme>
<programme start="20210203013900 +0800" stop="20210203022400 +0800" channel="IPTV法治">
<title lang="zh">普法栏目剧</title>
</programme>
<programme start="20210203022400 +0800" stop="20210203025900 +0800" channel="IPTV法治">
<title lang="zh">热线12</title>
</programme>
<programme start="20210203025900 +0800" stop="20210203031700 +0800" channel="IPTV法治">
<title lang="zh">道德观察(日播版)</title>
</programme>
<programme start="20210203031700 +0800" stop="20210203034400 +0800" channel="IPTV法治">
<title lang="zh">今日说法</title>
</programme>
<programme start="20210203034400 +0800" stop="20210203040800 +0800" channel="IPTV法治">
<title lang="zh">法治在线</title>
</programme>
<programme start="20210203040800 +0800" stop="20210203043500 +0800" channel="IPTV法治">
<title lang="zh">法律讲堂(生活版)</title>
</programme>
<programme start="20210203043500 +0800" stop="20210203050200 +0800" channel="IPTV法治">
<title lang="zh">法律讲堂(文史版)</title>
</programme>
<programme start="20210203050200 +0800" stop="20210203053200 +0800" channel="IPTV法治">
<title lang="zh">一线</title>
</programme>
<programme start="20210203053200 +0800" stop="20210203061700 +0800" channel="IPTV法治">
<title lang="zh">普法栏目剧</title>
</programme>
<programme start="20210203061700 +0800" stop="20210203065200 +0800" channel="IPTV法治">
<title lang="zh">热线12</title>
</programme>
<programme start="20210203065200 +0800" stop="20210203071000 +0800" channel="IPTV法治">
<title lang="zh">道德观察(日播版)</title>
</programme>
<programme start="20210203071000 +0800" stop="20210203073700 +0800" channel="IPTV法治">
<title lang="zh">今日说法</title>
</programme>
<programme start="20210203073700 +0800" stop="20210203080800 +0800" channel="IPTV法治">
<title lang="zh">法治在线</title>
</programme>
<programme start="20210203080800 +0800" stop="20210203083500 +0800" channel="IPTV法治">
<title lang="zh">法律讲堂(生活版)</title>
</programme>
<programme start="20210203083500 +0800" stop="20210203091600 +0800" channel="IPTV法治">
<title lang="zh">法律讲堂(文史版)</title>
</programme>
<programme start="20210203091600 +0800" stop="20210203093800 +0800" channel="IPTV法治">
<title lang="zh">一线</title>
</programme>
<programme start="20210203093800 +0800" stop="20210203101700 +0800" channel="IPTV法治">
<title lang="zh">普法栏目剧</title>
</programme>
<programme start="20210203101700 +0800" stop="20210203105200 +0800" channel="IPTV法治">
<title lang="zh">热线12</title>
</programme>
<programme start="20210203105200 +0800" stop="20210203111600 +0800" channel="IPTV法治">
<title lang="zh">道德观察(日播版)</title>
</programme>
<programme start="20210203111600 +0800" stop="20210203113200 +0800" channel="IPTV法治">
<title lang="zh">今日说法</title>
</programme>
<programme start="20210203113200 +0800" stop="20210203115100 +0800" channel="IPTV法治">
<title lang="zh">法治在线</title>
</programme>
<programme start="20210203115100 +0800" stop="20210203235950 +0800" channel="IPTV法治">
<title lang="zh">法律讲堂(生活版)</title>
</programme>
<programme start="20210202011500 +0800" stop="20210202014000 +0800" channel="IPTV3+">
<title lang="zh">综艺喜乐汇</title>
</programme>
<programme start="20210202014000 +0800" stop="20210202021500 +0800" channel="IPTV3+">
<title lang="zh">综艺喜乐汇</title>
</programme>
<programme start="20210202021500 +0800" stop="20210202033200 +0800" channel="IPTV3+">
<title lang="zh">幸福账单</title>
</programme>
<programme start="20210202033200 +0800" stop="20210202040200 +0800" channel="IPTV3+">
<title lang="zh">天天把歌唱</title>
</programme>
<programme start="20210202040200 +0800" stop="20210202051900 +0800" channel="IPTV3+">
<title lang="zh">开门大吉</title>
</programme>
<programme start="20210202051900 +0800" stop="20210202063600 +0800" channel="IPTV3+">
<title lang="zh">越战越勇</title>
</programme>
<programme start="20210202063600 +0800" stop="20210202080100 +0800" channel="IPTV3+">
<title lang="zh">出彩中国人</title>
</programme>
<programme start="20210202080100 +0800" stop="20210202091800 +0800" channel="IPTV3+">
<title lang="zh">黄金100秒</title>
</programme>
<programme start="20210202091800 +0800" stop="20210202103800 +0800" channel="IPTV3+">
<title lang="zh">星光大道</title>
</programme>
<programme start="20210202103800 +0800" stop="20210202114800 +0800" channel="IPTV3+">
<title lang="zh">星光大道</title>
</programme>
<programme start="20210202114800 +0800" stop="20210203011500 +0800" channel="IPTV3+">
<title lang="zh">非常6+1</title>
</programme>
<programme start="20210203011500 +0800" stop="20210203014000 +0800" channel="IPTV3+">
<title lang="zh">综艺喜乐汇</title>
</programme>
<programme start="20210203014000 +0800" stop="20210203021500 +0800" channel="IPTV3+">
<title lang="zh">综艺喜乐汇</title>
</programme>
<programme start="20210203021500 +0800" stop="20210203033200 +0800" channel="IPTV3+">
<title lang="zh">幸福账单</title>
</programme>
<programme start="20210203033200 +0800" stop="20210203040200 +0800" channel="IPTV3+">
<title lang="zh">天天把歌唱</title>
</programme>
<programme start="20210203040200 +0800" stop="20210203051900 +0800" channel="IPTV3+">
<title lang="zh">开门大吉</title>
</programme>
<programme start="20210203051900 +0800" stop="20210203063600 +0800" channel="IPTV3+">
<title lang="zh">越战越勇</title>
</programme>
<programme start="20210203063600 +0800" stop="20210203080100 +0800" channel="IPTV3+">
<title lang="zh">出彩中国人</title>
</programme>
<programme start="20210203080100 +0800" stop="20210203091800 +0800" channel="IPTV3+">
<title lang="zh">黄金100秒</title>
</programme>
<programme start="20210203091800 +0800" stop="20210203103800 +0800" channel="IPTV3+">
<title lang="zh">星光大道</title>
</programme>
<programme start="20210203103800 +0800" stop="20210203114800 +0800" channel="IPTV3+">
<title lang="zh">星光大道</title>
</programme>
<programme start="20210203114800 +0800" stop="20210203235950 +0800" channel="IPTV3+">
<title lang="zh">非常6+1</title>
</programme>
<programme start="20210202000000 +0800" stop="20210202015900 +0800" channel="IPTV5+">
<title lang="zh">《体育晨报》</title>
</programme>
<programme start="20210202015900 +0800" stop="20210202022800 +0800" channel="IPTV5+">
<title lang="zh">《体坛快讯》</title>
</programme>
<programme start="20210202022800 +0800" stop="20210202025500 +0800" channel="IPTV5+">
<title lang="zh">《体育新闻</title>
</programme>
<programme start="20210202025500 +0800" stop="20210202033400 +0800" channel="IPTV5+">
<title lang="zh">《体育世界》</title>
</programme>
<programme start="20210202033400 +0800" stop="20210202040800 +0800" channel="IPTV5+">
<title lang="zh">《天下足球》</title>
</programme>
<programme start="20210202040800 +0800" stop="20210202041500 +0800" channel="IPTV5+">
<title lang="zh">《风云会》</title>
</programme>
<programme start="20210202041500 +0800" stop="20210202043600 +0800" channel="IPTV5+">
<title lang="zh">《健身动起来》</title>
</programme>
<programme start="20210202043600 +0800" stop="20210202055500 +0800" channel="IPTV5+">
<title lang="zh">体育赛事</title>
</programme>
<programme start="20210202055500 +0800" stop="20210202072400 +0800" channel="IPTV5+">
<title lang="zh">体育赛事</title>
</programme>
<programme start="20210202072400 +0800" stop="20210202083500 +0800" channel="IPTV5+">
<title lang="zh">体育赛事</title>
</programme>
<programme start="20210202083500 +0800" stop="20210203000000 +0800" channel="IPTV5+">
<title lang="zh">体育赛事</title>
</programme>
<programme start="20210203000000 +0800" stop="20210203015900 +0800" channel="IPTV5+">
<title lang="zh">《体育晨报》</title>
</programme>
<programme start="20210203015900 +0800" stop="20210203022800 +0800" channel="IPTV5+">
<title lang="zh">《体坛快讯》</title>
</programme>
<programme start="20210203022800 +0800" stop="20210203025500 +0800" channel="IPTV5+">
<title lang="zh">《体育新闻</title>
</programme>
<programme start="20210203025500 +0800" stop="20210203033400 +0800" channel="IPTV5+">
<title lang="zh">《体育世界》</title>
</programme>
<programme start="20210203033400 +0800" stop="20210203040800 +0800" channel="IPTV5+">
<title lang="zh">《天下足球》</title>
</programme>
<programme start="20210203040800 +0800" stop="20210203041500 +0800" channel="IPTV5+">
<title lang="zh">《风云会》</title>
</programme>
<programme start="20210203041500 +0800" stop="20210203043600 +0800" channel="IPTV5+">
<title lang="zh">《健身动起来》</title>
</programme>
<programme start="20210203043600 +0800" stop="20210203055500 +0800" channel="IPTV5+">
<title lang="zh">体育赛事</title>
</programme>
<programme start="20210203055500 +0800" stop="20210203072400 +0800" channel="IPTV5+">
<title lang="zh">体育赛事</title>
</programme>
<programme start="20210203072400 +0800" stop="20210203083500 +0800" channel="IPTV5+">
<title lang="zh">体育赛事</title>
</programme>
<programme start="20210203083500 +0800" stop="20210203235950 +0800" channel="IPTV5+">
<title lang="zh">体育赛事</title>
</programme>
<programme start="20210202013100 +0800" stop="20210202025800 +0800" channel="IPTV6+">
<title lang="zh">经典影院</title>
</programme>
<programme start="20210202025800 +0800" stop="20210202043200 +0800" channel="IPTV6+">
<title lang="zh">经典影院</title>
</programme>
<programme start="20210202043200 +0800" stop="20210202055400 +0800" channel="IPTV6+">
<title lang="zh">经典影院</title>
</programme>
<programme start="20210202055400 +0800" stop="20210202071900 +0800" channel="IPTV6+">
<title lang="zh">经典影院</title>
</programme>
<programme start="20210202071900 +0800" stop="20210202085000 +0800" channel="IPTV6+">
<title lang="zh">经典影院</title>
</programme>
<programme start="20210202085000 +0800" stop="20210202102200 +0800" channel="IPTV6+">
<title lang="zh">经典影院</title>
</programme>
<programme start="20210202102200 +0800" stop="20210202114500 +0800" channel="IPTV6+">
<title lang="zh">经典影院</title>
</programme>
<programme start="20210202114500 +0800" stop="20210203013100 +0800" channel="IPTV6+">
<title lang="zh">经典影院</title>
</programme>
<programme start="20210203013100 +0800" stop="20210203025800 +0800" channel="IPTV6+">
<title lang="zh">经典影院</title>
</programme>
<programme start="20210203025800 +0800" stop="20210203043200 +0800" channel="IPTV6+">
<title lang="zh">经典影院</title>
</programme>
<programme start="20210203043200 +0800" stop="20210203055400 +0800" channel="IPTV6+">
<title lang="zh">经典影院</title>
</programme>
<programme start="20210203055400 +0800" stop="20210203071900 +0800" channel="IPTV6+">
<title lang="zh">经典影院</title>
</programme>
<programme start="20210203071900 +0800" stop="20210203085000 +0800" channel="IPTV6+">
<title lang="zh">经典影院</title>
</programme>
<programme start="20210203085000 +0800" stop="20210203102200 +0800" channel="IPTV6+">
<title lang="zh">经典影院</title>
</programme>
<programme start="20210203102200 +0800" stop="20210203114500 +0800" channel="IPTV6+">
<title lang="zh">经典影院</title>
</programme>
<programme start="20210203114500 +0800" stop="20210203235950 +0800" channel="IPTV6+">
<title lang="zh">经典影院</title>
</programme>
<programme start="20210202000400 +0800" stop="20210202020400 +0800" channel="IPTV8+">
<title lang="zh">电视剧</title>
</programme>
<programme start="20210202020400 +0800" stop="20210202064600 +0800" channel="IPTV8+">
<title lang="zh">电视剧</title>
</programme>
<programme start="20210202064600 +0800" stop="20210202093200 +0800" channel="IPTV8+">
<title lang="zh">电视剧</title>
</programme>
<programme start="20210202093200 +0800" stop="20210203000400 +0800" channel="IPTV8+">
<title lang="zh">电视剧</title>
</programme>
<programme start="20210203000400 +0800" stop="20210203020400 +0800" channel="IPTV8+">
<title lang="zh">电视剧</title>
</programme>
<programme start="20210203020400 +0800" stop="20210203064600 +0800" channel="IPTV8+">
<title lang="zh">电视剧</title>
</programme>
<programme start="20210203064600 +0800" stop="20210203093200 +0800" channel="IPTV8+">
<title lang="zh">电视剧</title>
</programme>
<programme start="20210203093200 +0800" stop="20210203235950 +0800" channel="IPTV8+">
<title lang="zh">电视剧</title>
</programme>
<programme start="20210202070100 +0800" stop="20210202073000 +0800" channel="济南综合">
<title lang="zh">济南新发现</title>
</programme>
<programme start="20210202073000 +0800" stop="20210202084300 +0800" channel="济南综合">
<title lang="zh">济南新闻(重播)</title>
</programme>
<programme start="20210202084300 +0800" stop="20210202092400 +0800" channel="济南综合">
<title lang="zh">济南新发现</title>
</programme>
<programme start="20210202092400 +0800" stop="20210202110000 +0800" channel="济南综合">
<title lang="zh">第一剧场</title>
</programme>
<programme start="20210202110000 +0800" stop="20210202111900 +0800" channel="济南综合">
<title lang="zh">榜样</title>
</programme>
<programme start="20210202111900 +0800" stop="20210202115000 +0800" channel="济南综合">
<title lang="zh">有么说么故事会(重播)</title>
</programme>
<programme start="20210202115000 +0800" stop="20210203070100 +0800" channel="济南综合">
<title lang="zh">新闻第一泉(直播)</title>
</programme>
<programme start="20210203070100 +0800" stop="20210203073000 +0800" channel="济南综合">
<title lang="zh">济南新发现</title>
</programme>
<programme start="20210203073000 +0800" stop="20210203084300 +0800" channel="济南综合">
<title lang="zh">济南新闻(重播)</title>
</programme>
<programme start="20210203084300 +0800" stop="20210203092400 +0800" channel="济南综合">
<title lang="zh">济南新发现</title>
</programme>
<programme start="20210203092400 +0800" stop="20210203110000 +0800" channel="济南综合">
<title lang="zh">第一剧场</title>
</programme>
<programme start="20210203110000 +0800" stop="20210203111900 +0800" channel="济南综合">
<title lang="zh">榜样</title>
</programme>
<programme start="20210203111900 +0800" stop="20210203115000 +0800" channel="济南综合">
<title lang="zh">有么说么故事会(重播)</title>
</programme>
<programme start="20210203115000 +0800" stop="20210203235950 +0800" channel="济南综合">
<title lang="zh">新闻第一泉(直播)</title>
</programme>
<programme start="20210202060000 +0800" stop="20210202060500 +0800" channel="临沂综合">
<title lang="zh">晨曲</title>
</programme>
<programme start="20210202060500 +0800" stop="20210202065500 +0800" channel="临沂综合">
<title lang="zh">中华养生</title>
</programme>
<programme start="20210202065500 +0800" stop="20210202071500 +0800" channel="临沂综合">
<title lang="zh">马上就办直通车</title>
</programme>
<programme start="20210202071500 +0800" stop="20210202075500 +0800" channel="临沂综合">
<title lang="zh">临沂新闻</title>
</programme>
<programme start="20210202075500 +0800" stop="20210202091500 +0800" channel="临沂综合">
<title lang="zh">电视剧</title>
</programme>
<programme start="20210202091500 +0800" stop="20210202103500 +0800" channel="临沂综合">
<title lang="zh">电视剧</title>
</programme>
<programme start="20210202103500 +0800" stop="20210202115000 +0800" channel="临沂综合">
<title lang="zh">电视剧</title>
</programme>
<programme start="20210202115000 +0800" stop="20210203060000 +0800" channel="临沂综合">
<title lang="zh">临沂新闻</title>
</programme>
<programme start="20210203060000 +0800" stop="20210203060500 +0800" channel="临沂综合">
<title lang="zh">晨曲</title>
</programme>
<programme start="20210203060500 +0800" stop="20210203065500 +0800" channel="临沂综合">
<title lang="zh">中华养生</title>
</programme>
<programme start="20210203065500 +0800" stop="20210203071500 +0800" channel="临沂综合">
<title lang="zh">马上就办直通车</title>
</programme>
<programme start="20210203071500 +0800" stop="20210203075500 +0800" channel="临沂综合">
<title lang="zh">临沂新闻</title>
</programme>
<programme start="20210203075500 +0800" stop="20210203091500 +0800" channel="临沂综合">
<title lang="zh">电视剧</title>
</programme>
<programme start="20210203091500 +0800" stop="20210203103500 +0800" channel="临沂综合">
<title lang="zh">电视剧</title>
</programme>
<programme start="20210203103500 +0800" stop="20210203115000 +0800" channel="临沂综合">
<title lang="zh">电视剧</title>
</programme>
<programme start="20210203115000 +0800" stop="20210203235950 +0800" channel="临沂综合">
<title lang="zh">临沂新闻</title>
</programme>
<programme start="20210202060000 +0800" stop="20210202063300 +0800" channel="临沂农科">
<title lang="zh">晨曲</title>
</programme>
<programme start="20210202063300 +0800" stop="20210202074500 +0800" channel="临沂农科">
<title lang="zh">琅琊风云榜</title>
</programme>
<programme start="20210202074500 +0800" stop="20210202090000 +0800" channel="临沂农科">
<title lang="zh">电视剧</title>
</programme>
<programme start="20210202090000 +0800" stop="20210202104000 +0800" channel="临沂农科">
<title lang="zh">电视剧</title>
</programme>
<programme start="20210202104000 +0800" stop="20210202115000 +0800" channel="临沂农科">
<title lang="zh">室内剧</title>
</programme>
<programme start="20210202115000 +0800" stop="20210203060000 +0800" channel="临沂农科">
<title lang="zh">八点新时空</title>
</programme>
<programme start="20210203060000 +0800" stop="20210203063300 +0800" channel="临沂农科">
<title lang="zh">晨曲</title>
</programme>
<programme start="20210203063300 +0800" stop="20210203074500 +0800" channel="临沂农科">
<title lang="zh">琅琊风云榜</title>
</programme>
<programme start="20210203074500 +0800" stop="20210203090000 +0800" channel="临沂农科">
<title lang="zh">电视剧</title>
</programme>
<programme start="20210203090000 +0800" stop="20210203104000 +0800" channel="临沂农科">
<title lang="zh">电视剧</title>
</programme>
<programme start="20210203104000 +0800" stop="20210203115000 +0800" channel="临沂农科">
<title lang="zh">室内剧</title>
</programme>
<programme start="20210203115000 +0800" stop="20210203235950 +0800" channel="临沂农科">
<title lang="zh">八点新时空</title>
</programme>
<programme start="20210202060000 +0800" stop="20210202063000 +0800" channel="临沂公共">
<title lang="zh">晨曲</title>
</programme>
<programme start="20210202063000 +0800" stop="20210202070000 +0800" channel="临沂公共">
<title lang="zh">娱乐现场</title>
</programme>
<programme start="20210202070000 +0800" stop="20210202073000 +0800" channel="临沂公共">
<title lang="zh">直播临沂</title>
</programme>
<programme start="20210202073000 +0800" stop="20210202082200 +0800" channel="临沂公共">
<title lang="zh">行风热线</title>
</programme>
<programme start="20210202082200 +0800" stop="20210202093000 +0800" channel="临沂公共">
<title lang="zh">直播挑战</title>
</programme>
<programme start="20210202093000 +0800" stop="20210202103000 +0800" channel="临沂公共">
<title lang="zh">电视剧</title>
</programme>
<programme start="20210202103000 +0800" stop="20210203060000 +0800" channel="临沂公共">
<title lang="zh">电视剧</title>
</programme>
<programme start="20210203060000 +0800" stop="20210203063000 +0800" channel="临沂公共">
<title lang="zh">晨曲</title>
</programme>
<programme start="20210203063000 +0800" stop="20210203070000 +0800" channel="临沂公共">
<title lang="zh">娱乐现场</title>
</programme>
<programme start="20210203070000 +0800" stop="20210203073000 +0800" channel="临沂公共">
<title lang="zh">直播临沂</title>
</programme>
<programme start="20210203073000 +0800" stop="20210203082200 +0800" channel="临沂公共">
<title lang="zh">行风热线</title>
</programme>
<programme start="20210203082200 +0800" stop="20210203093000 +0800" channel="临沂公共">
<title lang="zh">直播挑战</title>
</programme>
<programme start="20210203093000 +0800" stop="20210203103000 +0800" channel="临沂公共">
<title lang="zh">电视剧</title>
</programme>
<programme start="20210203103000 +0800" stop="20210203235950 +0800" channel="临沂公共">
<title lang="zh">电视剧</title>
</programme>
</tv>
